{"models":[{"hacker":"Stringrays","hacker_id":255,"rank":1241,"score":125.666698,"country":"India"},{"hacker":"AUBTeam6","hacker_id":2125,"rank":1242,"score":125.4,"country":"Lebanon"},{"hacker":"Glitchbusters","hacker_id":599,"rank":1243,"score":125.25,"country":"USA"},{"hacker":"Patras0101","hacker_id":2284,"rank":1244,"score":124.499943,"country":"Greece"},{"hacker":"MatlabDesingners","hacker_id":728,"rank":1245,"score":124.4,"country":"Mexico"},{"hacker":"RCDM","hacker_id":678,"rank":1246,"score":124.25,"country":"India"},{"hacker":"Gnosis","hacker_id":1284,"rank":1247,"score":122.799971,"country":"India"},{"hacker":"Kamui","hacker_id":1661,"rank":1248,"score":122.666698,"country":"India"},{"hacker":"BZU5","hacker_id":456,"rank":1249,"score":122.208366,"country":"Palestine"},{"hacker":"ZCoders","hacker_id":696,"rank":1250,"score":121.333302,"country":"India"}],"current_hacker":{"hacker":"RageQuit1","hacker_id":1668,"rank":33,"score":1447.602791,"country":"Canada"},"page":125,"total":1840}