{"models":[{"hacker":"beredim","hacker_id":2460,"rank":1521,"score":42.0,"country":null},{"hacker":"blitzkrieg1","hacker_id":2183,"rank":1522,"score":42.0,"country":"India"},{"hacker":"BattleOf1937","hacker_id":697,"rank":1523,"score":42.0,"country":"India"},{"hacker":"xtremeGG","hacker_id":824,"rank":1524,"score":42.0,"country":"India"},{"hacker":"ISU3","hacker_id":1100,"rank":1525,"score":42.0,"country":"USA"},{"hacker":"SunSyncOrbits","hacker_id":2044,"rank":1526,"score":42.0,"country":"Canada"},{"hacker":"codecrackers34","hacker_id":1095,"rank":1527,"score":42.0,"country":"India"},{"hacker":"XProgrammers","hacker_id":1864,"rank":1528,"score":42.0,"country":"Greece"},{"hacker":"Thundercats","hacker_id":1195,"rank":1529,"score":42.0,"country":"USA"},{"hacker":"isecsPowa1","hacker_id":2099,"rank":1530,"score":42.0,"country":"Tunisia"}],"current_hacker":{"hacker":"RageQuit1","hacker_id":1668,"rank":33,"score":1447.602791,"country":"Canada"},"page":153,"total":1840}